vectordbs/__init__.py
vectordbs/datastore.py
vectordbs/factory.py
vectordbs/providers/llama_datastore.py
vectordbs/providers/milvus_datastore.py
vectordbs/providers/pinecone_datastore.py
vectordbs/providers/qdrant_datastore.py
vectordbs/providers/redis_datastore.py
vectordbs/providers/weaviate_datastore.py
vectordbs/providers/zilliz_datastore.py
vectordbs-0.1.0.dist-info/LICENSE
vectordbs-0.1.0.dist-info/METADATA
vectordbs-0.1.0.dist-info/WHEEL
vectordbs-0.1.0.dist-info/RECORD
