Metadata-Version: 2.1
Name: vectordbs
Version: 0.1.0
Summary: A python library that supports all vector databases specifically for LLM apps and frameworks
License: Apache 2.0
Author: Timothy Chen
Author-email: tnachen@gmail.com
Requires-Python: >=3.10,<4.0
Classifier: License :: Other/Proprietary License
Classifier: Programming Language :: Python :: 3
Classifier: Programming Language :: Python :: 3.10
Classifier: Programming Language :: Python :: 3.11
Requires-Dist: chromadb (>=0.3.21,<0.4.0)
Requires-Dist: pinecone-client (>=2.2.1,<3.0.0)
Requires-Dist: weaviate-client (>=3.15.5,<4.0.0)
